Workbook

Sheet Raw Data
A1: Order ID | B1: Date | C1: Region | D1: Category | E1: Product | F1: Sales Rep | G1: Units | H1: Unit Price | I1: Revenue | J1: Cost | K1: Profit | L1: Month # | M1: Month
A2: ORD-1068 | B2: 45660 | C2: North | D2: Sports | E2: Dumbbell Set | F2: Liam Chen | G2: 34 | H2: 89 | I2: =G2*H2 -> 3026 | J2: =ROUND(I2*0.629,2) -> 1903.35 | K2: =I2-J2 -> 1122.65 | L2: =MONTH(B2) -> 1 | M2: =TEXT(B2,"mmm") -> Jan
A3: ORD-1003 | B3: 45661 | C3: South | D3: Sports | E3: Tennis Racket | F3: Priya Nair | G3: 10 | H3: 69 | I3: =G3*H3 -> 690 | J3: =ROUND(I3*0.587,2) -> 405.03 | K3: =I3-J3 -> 284.97 | L3: =MONTH(B3) -> 1 | M3: =TEXT(B3,"mmm") -> Jan
A4: ORD-1135 | B4: 45665 | C4: South | D4: Sports | E4: Dumbbell Set | F4: Amara Okafor | G4: 31 | H4: 89 | I4: =G4*H4 -> 2759 | J4: =ROUND(I4*0.683,2) -> 1884.4 | K4: =I4-J4 -> 874.6 | L4: =MONTH(B4) -> 1 | M4: =TEXT(B4,"mmm") -> Jan
A5: ORD-1224 | B5: 45667 | C5: East | D5: Apparel | E5: Winter Jacket | F5: Sofia Rossi | G5: 39 | H5: 129 | I5: =G5*H5 -> 5031 | J5: =ROUND(I5*0.64,2) -> 3219.84 | K5: =I5-J5 -> 1811.16 | L5: =MONTH(B5) -> 1 | M5: =TEXT(B5,"mmm") -> Jan
A6: ORD-1118 | B6: 45668 | C6: East | D6: Electronics | E6: 4K Monitor | F6: Diego Fernandez | G6: 34 | H6: 289 | I6: =G6*H6 -> 9826 | J6: =ROUND(I6*0.661,2) -> 6494.99 | K6: =I6-J6 -> 3331.01 | L6: =MONTH(B6) -> 1 | M6: =TEXT(B6,"mmm") -> Jan
A7: ORD-1086 | B7: 45671 | C7: East | D7: Sports | E7: Camping Tent | F7: Kwame Mensah | G7: 13 | H7: 159 | I7: =G7*H7 -> 2067 | J7: =ROUND(I7*0.563,2) -> 1163.72 | K7: =I7-J7 -> 903.28 | L7: =MONTH(B7) -> 1 | M7: =TEXT(B7,"mmm") -> Jan
A8: ORD-1220 | B8: 45671 | C8: West | D8: Electronics | E8: Bluetooth Speaker | F8: Sofia Rossi | G8: 24 | H8: 45 | I8: =G8*H8 -> 1080 | J8: =ROUND(I8*0.59,2) -> 637.2 | K8: =I8-J8 -> 442.8 | L8: =MONTH(B8) -> 1 | M8: =TEXT(B8,"mmm") -> Jan
A9: ORD-1251 | B9: 45671 | C9: East | D9: Home & Garden | E9: Garden Hose | F9: Sofia Rossi | G9: 9 | H9: 22 | I9: =G9*H9 -> 198 | J9: =ROUND(I9*0.654,2) -> 129.49 | K9: =I9-J9 -> 68.51 | L9: =MONTH(B9) -> 1 | M9: =TEXT(B9,"mmm") -> Jan
A10: ORD-1056 | B10: 45672 | C10: North | D10: Home & Garden | E10: Patio Chair | F10: Sofia Rossi | G10: 17 | H10: 74 | I10: =G10*H10 -> 1258 | J10: =ROUND(I10*0.557,2) -> 700.71 | K10: =I10-J10 -> 557.29 | L10: =MONTH(B10) -> 1 | M10: =TEXT(B10,"mmm") -> Jan
A11: ORD-1078 | B11: 45672 | C11: West | D11: Home & Garden | E11: Garden Hose | F11: Kwame Mensah | G11: 11 | H11: 22 | I11: =G11*H11 -> 242 | J11: =ROUND(I11*0.693,2) -> 167.71 | K11: =I11-J11 -> 74.29 | L11: =MONTH(B11) -> 1 | M11: =TEXT(B11,"mmm") -> Jan
A12: ORD-1139 | B12: 45672 | C12: North | D12: Home & Garden | E12: Cordless Vacuum | F12: Priya Nair | G12: 23 | H12: 199 | I12: =G12*H12 -> 4577 | J12: =ROUND(I12*0.614,2) -> 2810.28 | K12: =I12-J12 -> 1766.72 | L12: =MONTH(B12) -> 1 | M12: =TEXT(B12,"mmm") -> Jan
A13: ORD-1026 | B13: 45674 | C13: East | D13: Electronics | E13: 4K Monitor | F13: Priya Nair | G13: 32 | H13: 289 | I13: =G13*H13 -> 9248 | J13: =ROUND(I13*0.586,2) -> 5419.33 | K13: =I13-J13 -> 3828.67 | L13: =MONTH(B13) -> 1 | M13: =TEXT(B13,"mmm") -> Jan
A14: ORD-1053 | B14: 45677 | C14: West | D14: Apparel | E14: Winter Jacket | F14: Diego Fernandez | G14: 23 | H14: 129 | I14: =G14*H14 -> 2967 | J14: =ROUND(I14*0.602,2) -> 1786.13 | K14: =I14-J14 -> 1180.87 | L14: =MONTH(B14) -> 1 | M14: =TEXT(B14,"mmm") -> Jan
A15: ORD-1039 | B15: 45678 | C15: North | D15: Sports | E15: Tennis Racket | F15: Priya Nair | G15: 14 | H15: 69 | I15: =G15*H15 -> 966 | J15: =ROUND(I15*0.664,2) -> 641.42 | K15: =I15-J15 -> 324.58 | L15: =MONTH(B15) -> 1 | M15: =TEXT(B15,"mmm") -> Jan
A16: ORD-1234 | B16: 45679 | C16: East | D16: Home & Garden | E16: Garden Hose | F16: Sofia Rossi | G16: 31 | H16: 22 | I16: =G16*H16 -> 682 | J16: =ROUND(I16*0.593,2) -> 404.43 | K16: =I16-J16 -> 277.57 | L16: =MONTH(B16) -> 1 | M16: =TEXT(B16,"mmm") -> Jan
A17: ORD-1240 | B17: 45679 | C17: East | D17: Sports | E17: Tennis Racket | F17: Kwame Mensah | G17: 4 | H17: 69 | I17: =G17*H17 -> 276 | J17: =ROUND(I17*0.563,2) -> 155.39 | K17: =I17-J17 -> 120.61 | L17: =MONTH(B17) -> 1 | M17: =TEXT(B17,"mmm") -> Jan
A18: ORD-1007 | B18: 45681 | C18: South | D18: Home & Garden | E18: Cordless Vacuum | F18: Liam Chen | G18: 7 | H18: 199 | I18: =G18*H18 -> 1393 | J18: =ROUND(I18*0.615,2) -> 856.7 | K18: =I18-J18 -> 536.3 | L18: =MONTH(B18) -> 1 | M18: =TEXT(B18,"mmm") -> Jan
A19: ORD-1185 | B19: 45683 | C19: North | D19: Home & Garden | E19: Garden Hose | F19: Kwame Mensah | G19: 28 | H19: 22 | I19: =G19*H19 -> 616 | J19: =ROUND(I19*0.633,2) -> 389.93 | K19: =I19-J19 -> 226.07 | L19: =MONTH(B19) -> 1 | M19: =TEXT(B19,"mmm") -> Jan
A20: ORD-1178 | B20: 45684 | C20: East | D20: Home & Garden | E20: LED Lamp | F20: Amara Okafor | G20: 37 | H20: 29 | I20: =G20*H20 -> 1073 | J20: =ROUND(I20*0.636,2) -> 682.43 | K20: =I20-J20 -> 390.57 | L20: =MONTH(B20) -> 1 | M20: =TEXT(B20,"mmm") -> Jan
A21: ORD-1029 | B21: 45685 | C21: North | D21: Electronics | E21: Bluetooth Speaker | F21: Kwame Mensah | G21: 22 | H21: 45 | I21: =G21*H21 -> 990 | J21: =ROUND(I21*0.686,2) -> 679.14 | K21: =I21-J21 -> 310.86 | L21: =MONTH(B21) -> 1 | M21: =TEXT(B21,"mmm") -> Jan
A22: ORD-1255 | B22: 45686 | C22: North | D22: Apparel | E22: Denim Jeans | F22: Liam Chen | G22: 11 | H22: 54 | I22: =G22*H22 -> 594 | J22: =ROUND(I22*0.605,2) -> 359.37 | K22: =I22-J22 -> 234.63 | L22: =MONTH(B22) -> 1 | M22: =TEXT(B22,"mmm") -> Jan
A23: ORD-1233 | B23: 45690 | C23: West | D23: Electronics | E23: Smart Watch | F23: Liam Chen | G23: 3 | H23: 179 | I23: =G23*H23 -> 537 | J23: =ROUND(I23*0.684,2) -> 367.31 | K23: =I23-J23 -> 169.69 | L23: =MONTH(B23) -> 2 | M23: =TEXT(B23,"mmm") -> Feb
A24: ORD-1055 | B24: 45693 | C24: East | D24: Home & Garden | E24: Garden Hose | F24: Kwame Mensah | G24: 35 | H24: 22 | I24: =G24*H24 -> 770 | J24: =ROUND(I24*0.606,2) -> 466.62 | K24: =I24-J24 -> 303.38 | L24: =MONTH(B24) -> 2 | M24: =TEXT(B24,"mmm") -> Feb
A25: ORD-1041 | B25: 45695 | C25: North | D25: Sports | E25: Yoga Mat | F25: Amara Okafor | G25: 35 | H25: 24 | I25: =G25*H25 -> 840 | J25: =ROUND(I25*0.586,2) -> 492.24 | K25: =I25-J25 -> 347.76 | L25: =MONTH(B25) -> 2 | M25: =TEXT(B25,"mmm") -> Feb
A26: ORD-1192 | B26: 45697 | C26: East | D26: Sports | E26: Camping Tent | F26: Kwame Mensah | G26: 27 | H26: 159 | I26: =G26*H26 -> 4293 | J26: =ROUND(I26*0.599,2) -> 2571.51 | K26: =I26-J26 -> 1721.49 | L26: =MONTH(B26) -> 2 | M26: =TEXT(B26,"mmm") -> Feb
A27: ORD-1021 | B27: 45698 | C27: North | D27: Sports | E27: Yoga Mat | F27: Sofia Rossi | G27: 9 | H27: 24 | I27: =G27*H27 -> 216 | J27: =ROUND(I27*0.572,2) -> 123.55 | K27: =I27-J27 -> 92.45 | L27: =MONTH(B27) -> 2 | M27: =TEXT(B27,"mmm") -> Feb
A28: ORD-1221 | B28: 45699 | C28: East | D28: Apparel | E28: Running Shoes | F28: Priya Nair | G28: 7 | H28: 89 | I28: =G28*H28 -> 623 | J28: =ROUND(I28*0.693,2) -> 431.74 | K28: =I28-J28 -> 191.26 | L28: =MONTH(B28) -> 2 | M28: =TEXT(B28,"mmm") -> Feb
A29: ORD-1209 | B29: 45701 | C29: East | D29: Sports | E29: Tennis Racket | F29: Liam Chen | G29: 34 | H29: 69 | I29: =G29*H29 -> 2346 | J29: =ROUND(I29*0.566,2) -> 1327.84 | K29: =I29-J29 -> 1018.16 | L29: =MONTH(B29) -> 2 | M29: =TEXT(B29,"mmm") -> Feb
A30: ORD-1252 | B30: 45702 | C30: North | D30: Home & Garden | E30: Garden Hose | F30: Kwame Mensah | G30: 31 | H30: 22 | I30: =G30*H30 -> 682 | J30: =ROUND(I30*0.639,2) -> 435.8 | K30: =I30-J30 -> 246.2 | L30: =MONTH(B30) -> 2 | M30: =TEXT(B30,"mmm") -> Feb
A31: ORD-1138 | B31: 45704 | C31: West | D31: Electronics | E31: Wireless Earbuds | F31: Diego Fernandez | G31: 11 | H31: 59 | I31: =G31*H31 -> 649 | J31: =ROUND(I31*0.668,2) -> 433.53 | K31: =I31-J31 -> 215.47 | L31: =MONTH(B31) -> 2 | M31: =TEXT(B31,"mmm") -> Feb
A32: ORD-1202 | B32: 45704 | C32: West | D32: Sports | E32: Yoga Mat | F32: Diego Fernandez | G32: 37 | H32: 24 | I32: =G32*H32 -> 888 | J32: =ROUND(I32*0.661,2) -> 586.97 | K32: =I32-J32 -> 301.03 | L32: =MONTH(B32) -> 2 | M32: =TEXT(B32,"mmm") -> Feb
A33: ORD-1176 | B33: 45707 | C33: East | D33: Apparel | E33: Running Shoes | F33: Sofia Rossi | G33: 36 | H33: 89 | I33: =G33*H33 -> 3204 | J33: =ROUND(I33*0.645,2) -> 2066.58 | K33: =I33-J33 -> 1137.42 | L33: =MONTH(B33) -> 2 | M33: =TEXT(B33,"mmm") -> Feb
A34: ORD-1109 | B34: 45708 | C34: South | D34: Apparel | E34: Denim Jeans | F34: Kwame Mensah | G34: 6 | H34: 54 | I34: =G34*H34 -> 324 | J34: =ROUND(I34*0.577,2) -> 186.95 | K34: =I34-J34 -> 137.05 | L34: =MONTH(B34) -> 2 | M34: =TEXT(B34,"mmm") -> Feb
A35: ORD-1001 | B35: 45710 | C35: North | D35: Sports | E35: Yoga Mat | F35: Amara Okafor | G35: 6 | H35: 24 | I35: =G35*H35 -> 144 | J35: =ROUND(I35*0.587,2) -> 84.53 | K35: =I35-J35 -> 59.47 | L35: =MONTH(B35) -> 2 | M35: =TEXT(B35,"mmm") -> Feb
A36: ORD-1030 | B36: 45713 | C36: South | D36: Apparel | E36: Winter Jacket | F36: Sofia Rossi | G36: 29 | H36: 129 | I36: =G36*H36 -> 3741 | J36: =ROUND(I36*0.574,2) -> 2147.33 | K36: =I36-J36 -> 1593.67 | L36: =MONTH(B36) -> 2 | M36: =TEXT(B36,"mmm") -> Feb
A37: ORD-1168 | B37: 45713 | C37: West | D37: Apparel | E37: Running Shoes | F37: Kwame Mensah | G37: 34 | H37: 89 | I37: =G37*H37 -> 3026 | J37: =ROUND(I37*0.601,2) -> 1818.63 | K37: =I37-J37 -> 1207.37 | L37: =MONTH(B37) -> 2 | M37: =TEXT(B37,"mmm") -> Feb
A38: ORD-1187 | B38: 45714 | C38: East | D38: Sports | E38: Tennis Racket | F38: Amara Okafor | G38: 15 | H38: 69 | I38: =G38*H38 -> 1035 | J38: =ROUND(I38*0.617,2) -> 638.6 | K38: =I38-J38 -> 396.4 | L38: =MONTH(B38) -> 2 | M38: =TEXT(B38,"mmm") -> Feb
A39: ORD-1225 | B39: 45714 | C39: East | D39: Apparel | E39: Denim Jeans | F39: Amara Okafor | G39: 4 | H39: 54 | I39: =G39*H39 -> 216 | J39: =ROUND(I39*0.591,2) -> 127.66 | K39: =I39-J39 -> 88.34 | L39: =MONTH(B39) -> 2 | M39: =TEXT(B39,"mmm") -> Feb
A40: ORD-1020 | B40: 45715 | C40: East | D40: Home & Garden | E40: Patio Chair | F40: Amara Okafor | G40: 16 | H40: 74 | I40: =G40*H40 -> 1184 | J40: =ROUND(I40*0.699,2) -> 827.62 | K40: =I40-J40 -> 356.38 | L40: =MONTH(B40) -> 2 | M40: =TEXT(B40,"mmm") -> Feb
A41: ORD-1048 | B41: 45715 | C41: North | D41: Apparel | E41: Running Shoes | F41: Priya Nair | G41: 38 | H41: 89 | I41: =G41*H41 -> 3382 | J41: =ROUND(I41*0.644,2) -> 2178.01 | K41: =I41-J41 -> 1203.99 | L41: =MONTH(B41) -> 2 | M41: =TEXT(B41,"mmm") -> Feb
A42: ORD-1126 | B42: 45716 | C42: West | D42: Electronics | E42: 4K Monitor | F42: Diego Fernandez | G42: 19 | H42: 289 | I42: =G42*H42 -> 5491 | J42: =ROUND(I42*0.637,2) -> 3497.77 | K42: =I42-J42 -> 1993.23 | L42: =MONTH(B42) -> 2 | M42: =TEXT(B42,"mmm") -> Feb
A43: ORD-1058 | B43: 45717 | C43: West | D43: Apparel | E43: Denim Jeans | F43: Amara Okafor | G43: 28 | H43: 54 | I43: =G43*H43 -> 1512 | J43: =ROUND(I43*0.55,2) -> 831.6 | K43: =I43-J43 -> 680.4 | L43: =MONTH(B43) -> 3 | M43: =TEXT(B43,"mmm") -> Mar
A44: ORD-1122 | B44: 45717 | C44: West | D44: Electronics | E44: Bluetooth Speaker | F44: Diego Fernandez | G44: 4 | H44: 45 | I44: =G44*H44 -> 180 | J44: =ROUND(I44*0.582,2) -> 104.76 | K44: =I44-J44 -> 75.24 | L44: =MONTH(B44) -> 3 | M44: =TEXT(B44,"mmm") -> Mar
A45: ORD-1099 | B45: 45719 | C45: South | D45: Home & Garden | E45: Cordless Vacuum | F45: Kwame Mensah | G45: 35 | H45: 199 | I45: =G45*H45 -> 6965 | J45: =ROUND(I45*0.712,2) -> 4959.08 | K45: =I45-J45 -> 2005.92 | L45: =MONTH(B45) -> 3 | M45: =TEXT(B45,"mmm") -> Mar
A46: ORD-1153 | B46: 45721 | C46: West | D46: Home & Garden | E46: LED Lamp | F46: Sofia Rossi | G46: 25 | H46: 29 | I46: =G46*H46 -> 725 | J46: =ROUND(I46*0.69,2) -> 500.25 | K46: =I46-J46 -> 224.75 | L46: =MONTH(B46) -> 3 | M46: =TEXT(B46,"mmm") -> Mar
A47: ORD-1163 | B47: 45722 | C47: South | D47: Electronics | E47: 4K Monitor | F47: Sofia Rossi | G47: 14 | H47: 289 | I47: =G47*H47 -> 4046 | J47: =ROUND(I47*0.688,2) -> 2783.65 | K47: =I47-J47 -> 1262.35 | L47: =MONTH(B47) -> 3 | M47: =TEXT(B47,"mmm") -> Mar
A48: ORD-1171 | B48: 45722 | C48: East | D48: Home & Garden | E48: Garden Hose | F48: Sofia Rossi | G48: 34 | H48: 22 | I48: =G48*H48 -> 748 | J48: =ROUND(I48*0.6,2) -> 448.8 | K48: =I48-J48 -> 299.2 | L48: =MONTH(B48) -> 3 | M48: =TEXT(B48,"mmm") -> Mar
A49: ORD-1079 | B49: 45723 | C49: North | D49: Sports | E49: Yoga Mat | F49: Amara Okafor | G49: 28 | H49: 24 | I49: =G49*H49 -> 672 | J49: =ROUND(I49*0.573,2) -> 385.06 | K49: =I49-J49 -> 286.94 | L49: =MONTH(B49) -> 3 | M49: =TEXT(B49,"mmm") -> Mar
A50: ORD-1047 | B50: 45724 | C50: East | D50: Apparel | E50: Graphic Tee | F50: Sofia Rossi | G50: 28 | H50: 19 | I50: =G50*H50 -> 532 | J50: =ROUND(I50*0.645,2) -> 343.14 | K50: =I50-J50 -> 188.86 | L50: =MONTH(B50) -> 3 | M50: =TEXT(B50,"mmm") -> Mar
A51: ORD-1027 | B51: 45725 | C51: West | D51: Apparel | E51: Graphic Tee | F51: Diego Fernandez | G51: 13 | H51: 19 | I51: =G51*H51 -> 247 | J51: =ROUND(I51*0.566,2) -> 139.8 | K51: =I51-J51 -> 107.2 | L51: =MONTH(B51) -> 3 | M51: =TEXT(B51,"mmm") -> Mar
A52: ORD-1149 | B52: 45725 | C52: North | D52: Home & Garden | E52: LED Lamp | F52: Kwame Mensah | G52: 27 | H52: 29 | I52: =G52*H52 -> 783 | J52: =ROUND(I52*0.58,2) -> 454.14 | K52: =I52-J52 -> 328.86 | L52: =MONTH(B52) -> 3 | M52: =TEXT(B52,"mmm") -> Mar
A53: ORD-1150 | B53: 45725 | C53: East | D53: Home & Garden | E53: Patio Chair | F53: Priya Nair | G53: 31 | H53: 74 | I53: =G53*H53 -> 2294 | J53: =ROUND(I53*0.714,2) -> 1637.92 | K53: =I53-J53 -> 656.08 | L53: =MONTH(B53) -> 3 | M53: =TEXT(B53,"mmm") -> Mar
A54: ORD-1044 | B54: 45726 | C54: East | D54: Electronics | E54: Wireless Earbuds | F54: Kwame Mensah | G54: 36 | H54: 59 | I54: =G54*H54 -> 2124 | J54: =ROUND(I54*0.576,2) -> 1223.42 | K54: =I54-J54 -> 900.58 | L54: =MONTH(B54) -> 3 | M54: =TEXT(B54,"mmm") -> Mar
A55: ORD-1014 | B55: 45728 | C55: West | D55: Electronics | E55: Wireless Earbuds | F55: Amara Okafor | G55: 10 | H55: 59 | I55: =G55*H55 -> 590 | J55: =ROUND(I55*0.657,2) -> 387.63 | K55: =I55-J55 -> 202.37 | L55: =MONTH(B55) -> 3 | M55: =TEXT(B55,"mmm") -> Mar
A56: ORD-1217 | B56: 45728 | C56: East | D56: Electronics | E56: Bluetooth Speaker | F56: Priya Nair | G56: 36 | H56: 45 | I56: =G56*H56 -> 1620 | J56: =ROUND(I56*0.709,2) -> 1148.58 | K56: =I56-J56 -> 471.42 | L56: =MONTH(B56) -> 3 | M56: =TEXT(B56,"mmm") -> Mar
A57: ORD-1114 | B57: 45730 | C57: North | D57: Electronics | E57: 4K Monitor | F57: Priya Nair | G57: 39 | H57: 289 | I57: =G57*H57 -> 11271 | J57: =ROUND(I57*0.677,2) -> 7630.47 | K57: =I57-J57 -> 3640.53 | L57: =MONTH(B57) -> 3 | M57: =TEXT(B57,"mmm") -> Mar
A58: ORD-1208 | B58: 45730 | C58: East | D58: Home & Garden | E58: Garden Hose | F58: Liam Chen | G58: 39 | H58: 22 | I58: =G58*H58 -> 858 | J58: =ROUND(I58*0.671,2) -> 575.72 | K58: =I58-J58 -> 282.28 | L58: =MONTH(B58) -> 3 | M58: =TEXT(B58,"mmm") -> Mar
A59: ORD-1140 | B59: 45732 | C59: South | D59: Sports | E59: Dumbbell Set | F59: Liam Chen | G59: 12 | H59: 89 | I59: =G59*H59 -> 1068 | J59: =ROUND(I59*0.563,2) -> 601.28 | K59: =I59-J59 -> 466.72 | L59: =MONTH(B59) -> 3 | M59: =TEXT(B59,"mmm") -> Mar
A60: ORD-1019 | B60: 45736 | C60: East | D60: Apparel | E60: Running Shoes | F60: Sofia Rossi | G60: 21 | H60: 89 | I60: =G60*H60 -> 1869 | J60: =ROUND(I60*0.633,2) -> 1183.08 | K60: =I60-J60 -> 685.92 | L60: =MONTH(B60) -> 3 | M60: =TEXT(B60,"mmm") -> Mar
A61: ORD-1213 | B61: 45736 | C61: South | D61: Apparel | E61: Winter Jacket | F61: Kwame Mensah | G61: 29 | H61: 129 | I61: =G61*H61 -> 3741 | J61: =ROUND(I61*0.557,2) -> 2083.74 | K61: =I61-J61 -> 1657.26 | L61: =MONTH(B61) -> 3 | M61: =TEXT(B61,"mmm") -> Mar
A62: ORD-1051 | B62: 45737 | C62: South | D62: Apparel | E62: Winter Jacket | F62: Diego Fernandez | G62: 2 | H62: 129 | I62: =G62*H62 -> 258 | J62: =ROUND(I62*0.58,2) -> 149.64 | K62: =I62-J62 -> 108.36 | L62: =MONTH(B62) -> 3 | M62: =TEXT(B62,"mmm") -> Mar
A63: ORD-1179 | B63: 45737 | C63: West | D63: Apparel | E63: Running Shoes | F63: Priya Nair | G63: 36 | H63: 89 | I63: =G63*H63 -> 3204 | J63: =ROUND(I63*0.612,2) -> 1960.85 | K63: =I63-J63 -> 1243.15 | L63: =MONTH(B63) -> 3 | M63: =TEXT(B63,"mmm") -> Mar
A64: ORD-1064 | B64: 45744 | C64: North | D64: Home & Garden | E64: LED Lamp | F64: Amara Okafor | G64: 16 | H64: 29 | I64: =G64*H64 -> 464 | J64: =ROUND(I64*0.664,2) -> 308.1 | K64: =I64-J64 -> 155.9 | L64: =MONTH(B64) -> 3 | M64: =TEXT(B64,"mmm") -> Mar
A65: ORD-1196 | B65: 45744 | C65: North | D65: Electronics | E65: 4K Monitor | F65: Priya Nair | G65: 23 | H65: 289 | I65: =G65*H65 -> 6647 | J65: =ROUND(I65*0.674,2) -> 4480.08 | K65: =I65-J65 -> 2166.92 | L65: =MONTH(B65) -> 3 | M65: =TEXT(B65,"mmm") -> Mar
A66: ORD-1110 | B66: 45746 | C66: North | D66: Apparel | E66: Running Shoes | F66: Diego Fernandez | G66: 29 | H66: 89 | I66: =G66*H66 -> 2581 | J66: =ROUND(I66*0.667,2) -> 1721.53 | K66: =I66-J66 -> 859.47 | L66: =MONTH(B66) -> 3 | M66: =TEXT(B66,"mmm") -> Mar
A67: ORD-1062 | B67: 45747 | C67: East | D67: Sports | E67: Yoga Mat | F67: Priya Nair | G67: 19 | H67: 24 | I67: =G67*H67 -> 456 | J67: =ROUND(I67*0.586,2) -> 267.22 | K67: =I67-J67 -> 188.78 | L67: =MONTH(B67) -> 3 | M67: =TEXT(B67,"mmm") -> Mar
A68: ORD-1190 | B68: 45747 | C68: South | D68: Sports | E68: Dumbbell Set | F68: Sofia Rossi | G68: 36 | H68: 89 | I68: =G68*H68 -> 3204 | J68: =ROUND(I68*0.692,2) -> 2217.17 | K68: =I68-J68 -> 986.83 | L68: =MONTH(B68) -> 3 | M68: =TEXT(B68,"mmm") -> Mar
A69: ORD-1031 | B69: 45751 | C69: East | D69: Sports | E69: Dumbbell Set | F69: Amara Okafor | G69: 29 | H69: 89 | I69: =G69*H69 -> 2581 | J69: =ROUND(I69*0.687,2) -> 1773.15 | K69: =I69-J69 -> 807.85 | L69: =MONTH(B69) -> 4 | M69: =TEXT(B69,"mmm") -> Apr
A70: ORD-1113 | B70: 45759 | C70: West | D70: Electronics | E70: 4K Monitor | F70: Kwame Mensah | G70: 10 | H70: 289 | I70: =G70*H70 -> 2890 | J70: =ROUND(I70*0.704,2) -> 2034.56 | K70: =I70-J70 -> 855.44 | L70: =MONTH(B70) -> 4 | M70: =TEXT(B70,"mmm") -> Apr
A71: ORD-1050 | B71: 45765 | C71: South | D71: Electronics | E71: Smart Watch | F71: Sofia Rossi | G71: 27 | H71: 179 | I71: =G71*H71 -> 4833 | J71: =ROUND(I71*0.716,2) -> 3460.43 | K71: =I71-J71 -> 1372.57 | L71: =MONTH(B71) -> 4 | M71: =TEXT(B71,"mmm") -> Apr
A72: ORD-1094 | B72: 45766 | C72: East | D72: Home & Garden | E72: LED Lamp | F72: Priya Nair | G72: 39 | H72: 29 | I72: =G72*H72 -> 1131 | J72: =ROUND(I72*0.669,2) -> 756.64 | K72: =I72-J72 -> 374.36 | L72: =MONTH(B72) -> 4 | M72: =TEXT(B72,"mmm") -> Apr
A73: ORD-1211 | B73: 45767 | C73: East | D73: Sports | E73: Dumbbell Set | F73: Liam Chen | G73: 9 | H73: 89 | I73: =G73*H73 -> 801 | J73: =ROUND(I73*0.576,2) -> 461.38 | K73: =I73-J73 -> 339.62 | L73: =MONTH(B73) -> 4 | M73: =TEXT(B73,"mmm") -> Apr
A74: ORD-1173 | B74: 45768 | C74: West | D74: Sports | E74: Dumbbell Set | F74: Diego Fernandez | G74: 22 | H74: 89 | I74: =G74*H74 -> 1958 | J74: =ROUND(I74*0.691,2) -> 1352.98 | K74: =I74-J74 -> 605.02 | L74: =MONTH(B74) -> 4 | M74: =TEXT(B74,"mmm") -> Apr
A75: ORD-1147 | B75: 45770 | C75: South | D75: Home & Garden | E75: Patio Chair | F75: Kwame Mensah | G75: 7 | H75: 74 | I75: =G75*H75 -> 518 | J75: =ROUND(I75*0.704,2) -> 364.67 | K75: =I75-J75 -> 153.33 | L75: =MONTH(B75) -> 4 | M75: =TEXT(B75,"mmm") -> Apr
A76: ORD-1065 | B76: 45773 | C76: South | D76: Apparel | E76: Running Shoes | F76: Amara Okafor | G76: 16 | H76: 89 | I76: =G76*H76 -> 1424 | J76: =ROUND(I76*0.717,2) -> 1021.01 | K76: =I76-J76 -> 402.99 | L76: =MONTH(B76) -> 4 | M76: =TEXT(B76,"mmm") -> Apr
A77: ORD-1152 | B77: 45773 | C77: West | D77: Home & Garden | E77: Cordless Vacuum | F77: Diego Fernandez | G77: 1 | H77: 199 | I77: =G77*H77 -> 199 | J77: =ROUND(I77*0.595,2) -> 118.41 | K77: =I77-J77 -> 80.59 | L77: =MONTH(B77) -> 4 | M77: =TEXT(B77,"mmm") -> Apr
A78: ORD-1054 | B78: 45774 | C78: South | D78: Electronics | E78: 4K Monitor | F78: Diego Fernandez | G78: 22 | H78: 289 | I78: =G78*H78 -> 6358 | J78: =ROUND(I78*0.597,2) -> 3795.73 | K78: =I78-J78 -> 2562.27 | L78: =MONTH(B78) -> 4 | M78: =TEXT(B78,"mmm") -> Apr
A79: ORD-1074 | B79: 45776 | C79: West | D79: Apparel | E79: Winter Jacket | F79: Amara Okafor | G79: 27 | H79: 129 | I79: =G79*H79 -> 3483 | J79: =ROUND(I79*0.619,2) -> 2155.98 | K79: =I79-J79 -> 1327.02 | L79: =MONTH(B79) -> 4 | M79: =TEXT(B79,"mmm") -> Apr
A80: ORD-1132 | B80: 45777 | C80: West | D80: Electronics | E80: Smart Watch | F80: Kwame Mensah | G80: 31 | H80: 179 | I80: =G80*H80 -> 5549 | J80: =ROUND(I80*0.67,2) -> 3717.83 | K80: =I80-J80 -> 1831.17 | L80: =MONTH(B80) -> 4 | M80: =TEXT(B80,"mmm") -> Apr
A81: ORD-1164 | B81: 45777 | C81: East | D81: Apparel | E81: Running Shoes | F81: Priya Nair | G81: 10 | H81: 89 | I81: =G81*H81 -> 890 | J81: =ROUND(I81*0.718,2) -> 639.02 | K81: =I81-J81 -> 250.98 | L81: =MONTH(B81) -> 4 | M81: =TEXT(B81,"mmm") -> Apr
A82: ORD-1073 | B82: 45778 | C82: East | D82: Home & Garden | E82: LED Lamp | F82: Sofia Rossi | G82: 6 | H82: 29 | I82: =G82*H82 -> 174 | J82: =ROUND(I82*0.574,2) -> 99.88 | K82: =I82-J82 -> 74.12 | L82: =MONTH(B82) -> 5 | M82: =TEXT(B82,"mmm") -> May
A83: ORD-1084 | B83: 45780 | C83: South | D83: Sports | E83: Yoga Mat | F83: Sofia Rossi | G83: 14 | H83: 24 | I83: =G83*H83 -> 336 | J83: =ROUND(I83*0.629,2) -> 211.34 | K83: =I83-J83 -> 124.66 | L83: =MONTH(B83) -> 5 | M83: =TEXT(B83,"mmm") -> May
A84: ORD-1215 | B84: 45780 | C84: East | D84: Sports | E84: Dumbbell Set | F84: Priya Nair | G84: 37 | H84: 89 | I84: =G84*H84 -> 3293 | J84: =ROUND(I84*0.717,2) -> 2361.08 | K84: =I84-J84 -> 931.92 | L84: =MONTH(B84) -> 5 | M84: =TEXT(B84,"mmm") -> May
A85: ORD-1096 | B85: 45781 | C85: West | D85: Sports | E85: Camping Tent | F85: Amara Okafor | G85: 6 | H85: 159 | I85: =G85*H85 -> 954 | J85: =ROUND(I85*0.6,2) -> 572.4 | K85: =I85-J85 -> 381.6 | L85: =MONTH(B85) -> 5 | M85: =TEXT(B85,"mmm") -> May
A86: ORD-1228 | B86: 45781 | C86: West | D86: Apparel | E86: Running Shoes | F86: Sofia Rossi | G86: 24 | H86: 89 | I86: =G86*H86 -> 2136 | J86: =ROUND(I86*0.562,2) -> 1200.43 | K86: =I86-J86 -> 935.57 | L86: =MONTH(B86) -> 5 | M86: =TEXT(B86,"mmm") -> May
A87: ORD-1092 | B87: 45783 | C87: North | D87: Home & Garden | E87: Garden Hose | F87: Liam Chen | G87: 30 | H87: 22 | I87: =G87*H87 -> 660 | J87: =ROUND(I87*0.647,2) -> 427.02 | K87: =I87-J87 -> 232.98 | L87: =MONTH(B87) -> 5 | M87: =TEXT(B87,"mmm") -> May
A88: ORD-1107 | B88: 45785 | C88: North | D88: Sports | E88: Dumbbell Set | F88: Sofia Rossi | G88: 25 | H88: 89 | I88: =G88*H88 -> 2225 | J88: =ROUND(I88*0.627,2) -> 1395.08 | K88: =I88-J88 -> 829.92 | L88: =MONTH(B88) -> 5 | M88: =TEXT(B88,"mmm") -> May
A89: ORD-1046 | B89: 45786 | C89: North | D89: Electronics | E89: Bluetooth Speaker | F89: Priya Nair | G89: 3 | H89: 45 | I89: =G89*H89 -> 135 | J89: =ROUND(I89*0.551,2) -> 74.39 | K89: =I89-J89 -> 60.61 | L89: =MONTH(B89) -> 5 | M89: =TEXT(B89,"mmm") -> May
A90: ORD-1230 | B90: 45787 | C90: North | D90: Home & Garden | E90: Cordless Vacuum | F90: Priya Nair | G90: 16 | H90: 199 | I90: =G90*H90 -> 3184 | J90: =ROUND(I90*0.675,2) -> 2149.2 | K90: =I90-J90 -> 1034.8 | L90: =MONTH(B90) -> 5 | M90: =TEXT(B90,"mmm") -> May
A91: ORD-1189 | B91: 45788 | C91: East | D91: Home & Garden | E91: Cordless Vacuum | F91: Amara Okafor | G91: 32 | H91: 199 | I91: =G91*H91 -> 6368 | J91: =ROUND(I91*0.677,2) -> 4311.14 | K91: =I91-J91 -> 2056.86 | L91: =MONTH(B91) -> 5 | M91: =TEXT(B91,"mmm") -> May
A92: ORD-1085 | B92: 45789 | C92: East | D92: Apparel | E92: Running Shoes | F92: Liam Chen | G92: 20 | H92: 89 | I92: =G92*H92 -> 1780 | J92: =ROUND(I92*0.568,2) -> 1011.04 | K92: =I92-J92 -> 768.96 | L92: =MONTH(B92) -> 5 | M92: =TEXT(B92,"mmm") -> May
A93: ORD-1018 | B93: 45792 | C93: South | D93: Electronics | E93: Smart Watch | F93: Kwame Mensah | G93: 33 | H93: 179 | I93: =G93*H93 -> 5907 | J93: =ROUND(I93*0.654,2) -> 3863.18 | K93: =I93-J93 -> 2043.82 | L93: =MONTH(B93) -> 5 | M93: =TEXT(B93,"mmm") -> May
A94: ORD-1042 | B94: 45793 | C94: South | D94: Home & Garden | E94: Cordless Vacuum | F94: Liam Chen | G94: 24 | H94: 199 | I94: =G94*H94 -> 4776 | J94: =ROUND(I94*0.598,2) -> 2856.05 | K94: =I94-J94 -> 1919.95 | L94: =MONTH(B94) -> 5 | M94: =TEXT(B94,"mmm") -> May
A95: ORD-1136 | B95: 45793 | C95: East | D95: Sports | E95: Yoga Mat | F95: Priya Nair | G95: 35 | H95: 24 | I95: =G95*H95 -> 840 | J95: =ROUND(I95*0.615,2) -> 516.6 | K95: =I95-J95 -> 323.4 | L95: =MONTH(B95) -> 5 | M95: =TEXT(B95,"mmm") -> May
A96: ORD-1091 | B96: 45796 | C96: West | D96: Sports | E96: Camping Tent | F96: Kwame Mensah | G96: 38 | H96: 159 | I96: =G96*H96 -> 6042 | J96: =ROUND(I96*0.596,2) -> 3601.03 | K96: =I96-J96 -> 2440.97 | L96: =MONTH(B96) -> 5 | M96: =TEXT(B96,"mmm") -> May
A97: ORD-1116 | B97: 45797 | C97: West | D97: Sports | E97: Yoga Mat | F97: Sofia Rossi | G97: 3 | H97: 24 | I97: =G97*H97 -> 72 | J97: =ROUND(I97*0.701,2) -> 50.47 | K97: =I97-J97 -> 21.53 | L97: =MONTH(B97) -> 5 | M97: =TEXT(B97,"mmm") -> May
A98: ORD-1127 | B98: 45797 | C98: West | D98: Sports | E98: Camping Tent | F98: Liam Chen | G98: 30 | H98: 159 | I98: =G98*H98 -> 4770 | J98: =ROUND(I98*0.644,2) -> 3071.88 | K98: =I98-J98 -> 1698.12 | L98: =MONTH(B98) -> 5 | M98: =TEXT(B98,"mmm") -> May
A99: ORD-1181 | B99: 45797 | C99: East | D99: Home & Garden | E99: LED Lamp | F99: Amara Okafor | G99: 12 | H99: 29 | I99: =G99*H99 -> 348 | J99: =ROUND(I99*0.698,2) -> 242.9 | K99: =I99-J99 -> 105.1 | L99: =MONTH(B99) -> 5 | M99: =TEXT(B99,"mmm") -> May
A100: ORD-1095 | B100: 45799 | C100: North | D100: Apparel | E100: Running Shoes | F100: Liam Chen | G100: 27 | H100: 89 | I100: =G100*H100 -> 2403 | J100: =ROUND(I100*0.633,2) -> 1521.1 | K100: =I100-J100 -> 881.9 | L100: =MONTH(B100) -> 5 | M100: =TEXT(B100,"mmm") -> May
...

Sheet Pivot Summary
A1: Pivot Summary
A2: Cross-tab summaries built with SUMIFS/SUMPRODUCT so every cell recalculates when Raw Data changes.
A4: Revenue by Region x Category
A5: Region | B5: Electronics | C5: Apparel | D5: Home & Garden | E5: Sports | F5: Total
A6: North | B6: =SUMIFS('Raw Data'!$I$2:$I$261,'Raw Data'!$C$2:$C$261,$A6,'Raw Data'!$D$2:$D$261,B$5) -> 36003 | C6: =SUMIFS('Raw Data'!$I$2:$I$261,'Raw Data'!$C$2:$C$261,$A6,'Raw Data'!$D$2:$D$261,C$5) -> 23798 | D6: =SUMIFS('Raw Data'!$I$2:$I$261,'Raw Data'!$C$2:$C$261,$A6,'Raw Data'!$D$2:$D$261,D$5) -> 31555 | E6: =SUMIFS('Raw Data'!$I$2:$I$261,'Raw Data'!$C$2:$C$261,$A6,'Raw Data'!$D$2:$D$261,E$5) -> 28465 | F6: =SUM(B6:E6) -> 119821
A7: South | B7: =SUMIFS('Raw Data'!$I$2:$I$261,'Raw Data'!$C$2:$C$261,$A7,'Raw Data'!$D$2:$D$261,B$5) -> 47938 | C7: =SUMIFS('Raw Data'!$I$2:$I$261,'Raw Data'!$C$2:$C$261,$A7,'Raw Data'!$D$2:$D$261,C$5) -> 23189 | D7: =SUMIFS('Raw Data'!$I$2:$I$261,'Raw Data'!$C$2:$C$261,$A7,'Raw Data'!$D$2:$D$261,D$5) -> 34335 | E7: =SUMIFS('Raw Data'!$I$2:$I$261,'Raw Data'!$C$2:$C$261,$A7,'Raw Data'!$D$2:$D$261,E$5) -> 28814 | F7: =SUM(B7:E7) -> 134276
A8: East | B8: =SUMIFS('Raw Data'!$I$2:$I$261,'Raw Data'!$C$2:$C$261,$A8,'Raw Data'!$D$2:$D$261,B$5) -> 63207 | C8: =SUMIFS('Raw Data'!$I$2:$I$261,'Raw Data'!$C$2:$C$261,$A8,'Raw Data'!$D$2:$D$261,C$5) -> 28927 | D8: =SUMIFS('Raw Data'!$I$2:$I$261,'Raw Data'!$C$2:$C$261,$A8,'Raw Data'!$D$2:$D$261,D$5) -> 28975 | E8: =SUMIFS('Raw Data'!$I$2:$I$261,'Raw Data'!$C$2:$C$261,$A8,'Raw Data'!$D$2:$D$261,E$5) -> 42042 | F8: =SUM(B8:E8) -> 163151
A9: West | B9: =SUMIFS('Raw Data'!$I$2:$I$261,'Raw Data'!$C$2:$C$261,$A9,'Raw Data'!$D$2:$D$261,B$5) -> 45098 | C9: =SUMIFS('Raw Data'!$I$2:$I$261,'Raw Data'!$C$2:$C$261,$A9,'Raw Data'!$D$2:$D$261,C$5) -> 19936 | D9: =SUMIFS('Raw Data'!$I$2:$I$261,'Raw Data'!$C$2:$C$261,$A9,'Raw Data'!$D$2:$D$261,D$5) -> 21467 | E9: =SUMIFS('Raw Data'!$I$2:$I$261,'Raw Data'!$C$2:$C$261,$A9,'Raw Data'!$D$2:$D$261,E$5) -> 23693 | F9: =SUM(B9:E9) -> 110194
A10: Total | B10: =SUM(B6:B9) -> 192246 | C10: =SUM(C6:C9) -> 95850 | D10: =SUM(D6:D9) -> 116332 | E10: =SUM(E6:E9) -> 123014 | F10: =SUM(F6:F9) -> 527442
A13: Monthly Revenue & Profit Trend
A14: Month | B14: Revenue | C14: Profit | D14: Units Sold
A15: Jan | B15: =SUMIFS('Raw Data'!$I$2:$I$261,'Raw Data'!$L$2:$L$261,1) -> 49559 | C15: =SUMIFS('Raw Data'!$K$2:$K$261,'Raw Data'!$L$2:$L$261,1) -> 18668.01 | D15: =SUMIFS('Raw Data'!$G$2:$G$261,'Raw Data'!$L$2:$L$261,1) -> 454
A16: Feb | B16: =SUMIFS('Raw Data'!$I$2:$I$261,'Raw Data'!$L$2:$L$261,2) -> 33591 | C16: =SUMIFS('Raw Data'!$K$2:$K$261,'Raw Data'!$L$2:$L$261,2) -> 12780.21 | D16: =SUMIFS('Raw Data'!$G$2:$G$261,'Raw Data'!$L$2:$L$261,2) -> 432
A17: Mar | B17: =SUMIFS('Raw Data'!$I$2:$I$261,'Raw Data'!$L$2:$L$261,3) -> 58659 | C17: =SUMIFS('Raw Data'!$K$2:$K$261,'Raw Data'!$L$2:$L$261,3) -> 20132.29 | D17: =SUMIFS('Raw Data'!$G$2:$G$261,'Raw Data'!$L$2:$L$261,3) -> 650
A18: Apr | B18: =SUMIFS('Raw Data'!$I$2:$I$261,'Raw Data'!$L$2:$L$261,4) -> 32615 | C18: =SUMIFS('Raw Data'!$K$2:$K$261,'Raw Data'!$L$2:$L$261,4) -> 10963.21 | D18: =SUMIFS('Raw Data'!$G$2:$G$261,'Raw Data'!$L$2:$L$261,4) -> 250
A19: May | B19: =SUMIFS('Raw Data'!$I$2:$I$261,'Raw Data'!$L$2:$L$261,5) -> 54903 | C19: =SUMIFS('Raw Data'!$K$2:$K$261,'Raw Data'!$L$2:$L$261,5) -> 20122.69 | D19: =SUMIFS('Raw Data'!$G$2:$G$261,'Raw Data'!$L$2:$L$261,5) -> 541
A20: Jun | B20: =SUMIFS('Raw Data'!$I$2:$I$261,'Raw Data'!$L$2:$L$261,6) -> 29678 | C20: =SUMIFS('Raw Data'!$K$2:$K$261,'Raw Data'!$L$2:$L$261,6) -> 10186.67 | D20: =SUMIFS('Raw Data'!$G$2:$G$261,'Raw Data'!$L$2:$L$261,6) -> 275
A21: Jul | B21: =SUMIFS('Raw Data'!$I$2:$I$261,'Raw Data'!$L$2:$L$261,7) -> 39748 | C21: =SUMIFS('Raw Data'!$K$2:$K$261,'Raw Data'!$L$2:$L$261,7) -> 14626.25 | D21: =SUMIFS('Raw Data'!$G$2:$G$261,'Raw Data'!$L$2:$L$261,7) -> 502
A22: Aug | B22: =SUMIFS('Raw Data'!$I$2:$I$261,'Raw Data'!$L$2:$L$261,8) -> 38716 | C22: =SUMIFS('Raw Data'!$K$2:$K$261,'Raw Data'!$L$2:$L$261,8) -> 14675.72 | D22: =SUMIFS('Raw Data'!$G$2:$G$261,'Raw Data'!$L$2:$L$261,8) -> 384
A23: Sep | B23: =SUMIFS('Raw Data'!$I$2:$I$261,'Raw Data'!$L$2:$L$261,9) -> 41082 | C23: =SUMIFS('Raw Data'!$K$2:$K$261,'Raw Data'!$L$2:$L$261,9) -> 14673.14 | D23: =SUMIFS('Raw Data'!$G$2:$G$261,'Raw Data'!$L$2:$L$261,9) -> 478
A24: Oct | B24: =SUMIFS('Raw Data'!$I$2:$I$261,'Raw Data'!$L$2:$L$261,10) -> 41637 | C24: =SUMIFS('Raw Data'!$K$2:$K$261,'Raw Data'!$L$2:$L$261,10) -> 14805.88 | D24: =SUMIFS('Raw Data'!$G$2:$G$261,'Raw Data'!$L$2:$L$261,10) -> 495
A25: Nov | B25: =SUMIFS('Raw Data'!$I$2:$I$261,'Raw Data'!$L$2:$L$261,11) -> 51888 | C25: =SUMIFS('Raw Data'!$K$2:$K$261,'Raw Data'!$L$2:$L$261,11) -> 18800.27 | D25: =SUMIFS('Raw Data'!$G$2:$G$261,'Raw Data'!$L$2:$L$261,11) -> 472
A26: Dec | B26: =SUMIFS('Raw Data'!$I$2:$I$261,'Raw Data'!$L$2:$L$261,12) -> 55366 | C26: =SUMIFS('Raw Data'!$K$2:$K$261,'Raw Data'!$L$2:$L$261,12) -> 20500 | D26: =SUMIFS('Raw Data'!$G$2:$G$261,'Raw Data'!$L$2:$L$261,12) -> 515
A29: Sales Rep Leaderboard
A30: Sales Rep | B30: Revenue | C30: Profit | D30: Orders | E30: Avg Order Value
A31: Amara Okafor | B31: =SUMIFS('Raw Data'!$I$2:$I$261,'Raw Data'!$F$2:$F$261,$A31) -> 75061 | C31: =SUMIFS('Raw Data'!$K$2:$K$261,'Raw Data'!$F$2:$F$261,$A31) -> 26462.22 | D31: =COUNTIFS('Raw Data'!$F$2:$F$261,$A31) -> 51 | E31: =IFERROR(B31/D31,0) -> 1471.7843
A32: Liam Chen | B32: =SUMIFS('Raw Data'!$I$2:$I$261,'Raw Data'!$F$2:$F$261,$A32) -> 81688 | C32: =SUMIFS('Raw Data'!$K$2:$K$261,'Raw Data'!$F$2:$F$261,$A32) -> 29953.17 | D32: =COUNTIFS('Raw Data'!$F$2:$F$261,$A32) -> 49 | E32: =IFERROR(B32/D32,0) -> 1667.102
A33: Kwame Mensah | B33: =SUMIFS('Raw Data'!$I$2:$I$261,'Raw Data'!$F$2:$F$261,$A33) -> 121371 | C33: =SUMIFS('Raw Data'!$K$2:$K$261,'Raw Data'!$F$2:$F$261,$A33) -> 43930.75 | D33: =COUNTIFS('Raw Data'!$F$2:$F$261,$A33) -> 48 | E33: =IFERROR(B33/D33,0) -> 2528.5625
A34: Priya Nair | B34: =SUMIFS('Raw Data'!$I$2:$I$261,'Raw Data'!$F$2:$F$261,$A34) -> 107330 | C34: =SUMIFS('Raw Data'!$K$2:$K$261,'Raw Data'!$F$2:$F$261,$A34) -> 38769.76 | D34: =COUNTIFS('Raw Data'!$F$2:$F$261,$A34) -> 38 | E34: =IFERROR(B34/D34,0) -> 2824.4737
A35: Sofia Rossi | B35: =SUMIFS('Raw Data'!$I$2:$I$261,'Raw Data'!$F$2:$F$261,$A35) -> 69374 | C35: =SUMIFS('Raw Data'!$K$2:$K$261,'Raw Data'!$F$2:$F$261,$A35) -> 25827.41 | D35: =COUNTIFS('Raw Data'!$F$2:$F$261,$A35) -> 38 | E35: =IFERROR(B35/D35,0) -> 1825.6316
A36: Diego Fernandez | B36: =SUMIFS('Raw Data'!$I$2:$I$261,'Raw Data'!$F$2:$F$261,$A36) -> 72618 | C36: =SUMIFS('Raw Data'!$K$2:$K$261,'Raw Data'!$F$2:$F$261,$A36) -> 25991.03 | D36: =COUNTIFS('Raw Data'!$F$2:$F$261,$A36) -> 36 | E36: =IFERROR(B36/D36,0) -> 2017.1667

Sheet Dashboard
A1: Sales Performance Dashboard
A2: FY2025 | Interactive filters below drive every KPI card via SUMPRODUCT array formulas | K2: FALSE | L2: ◀ Tick to send the report now
A4: Region: | B4: All | D4: Category: | E4: All
A6: Total Revenue | C6: Total Profit | E6: Units Sold | G6: Orders | I6: Profit Margin
A7: =SUMPRODUCT(('Raw Data'!$C$2:$C$261=IF($B$4="All",'Raw Data'!$C$2:$C$261,$B$4))*('Raw Data'!$D$2:$D$261=IF($E$4="All",'Raw Data'!$D$2:$D$261,$E$4))*'Raw Data'!$I$2:$I$261) -> 527442 | C7: =SUMPRODUCT(('Raw Data'!$C$2:$C$261=IF($B$4="All",'Raw Data'!$C$2:$C$261,$B$4))*('Raw Data'!$D$2:$D$261=IF($E$4="All",'Raw Data'!$D$2:$D$261,$E$4))*'Raw Data'!$K$2:$K$261) -> 190934.34 | E7: =SUMPRODUCT(('Raw Data'!$C$2:$C$261=IF($B$4="All",'Raw Data'!$C$2:$C$261,$B$4))*('Raw Data'!$D$2:$D$261=IF($E$4="All",'Raw Data'!$D$2:$D$261,$E$4))*'Raw Data'!$G$2:$G$261) -> 5448 | G7: =SUMPRODUCT(('Raw Data'!$C$2:$C$261=IF($B$4="All",'Raw Data'!$C$2:$C$261,$B$4))*('Raw Data'!$D$2:$D$261=IF($E$4="All",'Raw Data'!$D$2:$D$261,$E$4))) -> 260 | I7: =IFERROR(SUMPRODUCT(('Raw Data'!$C$2:$C$261=IF($B$4="All",'Raw Data'!$C$2:$C$261,$B$4))*('Raw Data'!$D$2:$D$261=IF($E$4="All",'Raw Data'!$D$2:$D$261,$E$4))*'Raw Data'!$K$2:$K$261)/SUMPRODUCT(('Raw Data'!$C$2:$C$261=IF($B$4="All",'Raw Data'!$C$2:$C$261,$B$4))*('Raw Data'!$D$2:$D$261=IF($E$4="All",'Raw Data'!$D$2:$D$261,$E$4))*'Raw Data'!$I$2:$I$261),0) -> 0.36200064
A10: Revenue by Region | F10: Category Share
A28: Monthly Revenue Trend | I28: Top Sales Reps
I29: Sales Rep | J29: Revenue
I30: ='Pivot Summary'!A31 -> Amara Okafor | J30: ='Pivot Summary'!B31 -> 75061
I31: ='Pivot Summary'!A32 -> Liam Chen | J31: ='Pivot Summary'!B32 -> 81688
I32: ='Pivot Summary'!A33 -> Kwame Mensah | J32: ='Pivot Summary'!B33 -> 121371
I33: ='Pivot Summary'!A34 -> Priya Nair | J33: ='Pivot Summary'!B34 -> 107330
I34: ='Pivot Summary'!A35 -> Sofia Rossi | J34: ='Pivot Summary'!B35 -> 69374
I35: ='Pivot Summary'!A36 -> Diego Fernandez | J35: ='Pivot Summary'!B36 -> 72618

Sheet Recipients
A1: Email | B1: Name (optional)
A2: muthusimat2@gmail.com | B2: Stakeholder One

Sheet Read Me
A3: How this workbook is built
A4: • Raw Data: a structured Excel Table (SalesData) with 260 orders. Revenue, Cost, Profit, and Month are all formulas. Edit or extend the raw rows and everything downstream recalculates.
A5: • Pivot Summary: cross-tab and trend tables built with SUMIFS/COUNTIFS. The same result as an Excel/Google Sheets PivotTable, but formula-driven so it survives file conversion and recalculates automatically.
A6: • Dashboard: KPI cards and charts driven by two dropdown filters (Region, Category). The KPI formulas use SUMPRODUCT with an embedded IF which is an Excel native equivalent of an array formula, to let 'All' mean 'ignore this filter'.
A7: Turning this into a native PivotTable
A8: 1. Select any cell inside the SalesData table on the Raw Data tab.
A9: 2. Excel: Insert → PivotTable → New Worksheet. Google Sheets: Insert → Pivot table.
A10: 3. Drag Region / Category to Rows or Columns, and Revenue / Profit to Values.
A11: 4. Right-click → Refresh any time you add rows to Raw Data.
A13: Google Sheets equivalents (QUERY / ARRAYFORMULA)
A14: These functions are not supported by the recalculation engine used to build this file, so the workbook uses SUMIFS/SUMPRODUCT instead. If you upload this file to Google Sheets, you can replace the Pivot Summary and Dashboard formulas with the QUERY/ARRAYFORMULA versions below:
A15: Region x Category revenue (single formula, replaces the whole cross-tab):
... A29: • Add a new dropdown value to the Data Validation list on B4/E4 to filter by a new Region or Category once you add it to Raw Data.
